faiss/__init__.py
faiss/_swigfaiss.cpython-36m-darwin.so
faiss/setup.py
faiss/swigfaiss.py
faiss_cpu_noavx2-1.6.3.dist-info/LICENSE
faiss_cpu_noavx2-1.6.3.dist-info/METADATA
faiss_cpu_noavx2-1.6.3.dist-info/WHEEL
faiss_cpu_noavx2-1.6.3.dist-info/top_level.txt
faiss_cpu_noavx2-1.6.3.dist-info/RECORD
