Metadata-Version: 1.0
Name: faiss-cpu-noavx2
Version: 1.6.3
Summary: A library for efficient similarity search and clustering of dense vectors.
Home-page: https://github.com/kyamagu/faiss-wheels
Author: Kota Yamaguchi
Author-email: KotaYamaguchi1984@gmail.com
License: MIT
Keywords: search nearest neighbors
Platform: UNKNOWN
